CLASSIFIERS
LICENSE
MANIFEST.in
README.rst
requirements.pip
setup.py
src/django_nginx_ssi.egg-info/PKG-INFO
src/django_nginx_ssi.egg-info/SOURCES.txt
src/django_nginx_ssi.egg-info/dependency_links.txt
src/django_nginx_ssi.egg-info/requires.txt
src/django_nginx_ssi.egg-info/top_level.txt
src/ssi/__init__.py
src/ssi/models.py
src/ssi/tests.py
src/ssi/urls.py
src/ssi/utils.py
src/ssi/views.py
src/ssi/templatetags/__init__.py
src/ssi/templatetags/nginxssi_tags.py