Metadata-Version: 1.0
Name: django-nginx-ssi
Version: 0.1
Summary: Django SSI library for use with Nginx
Home-page: http://github.com/smn/django-nginx-ssi
Author: Simon de Haan
Author-email: simon@praekeltfoundation.org
License: BSD
Platform: UNKNOWN
Classifier: Development Status :: 3 - Alpha
Classifier: Intended Audience :: Developers
Classifier: License :: OSI Approved :: BSD License
Classifier: Operating System :: OS Independent
Classifier: Programming Language :: Python
Classifier: Framework :: Django
Classifier: Topic :: Software Development :: Libraries :: Python Modules
